eql/__init__.py
eql/__main__.py
eql/ast.py
eql/build.py
eql/engine.py
eql/errors.py
eql/events.py
eql/functions.py
eql/highlighters.py
eql/loader.py
eql/main.py
eql/optimizer.py
eql/parser.py
eql/pipes.py
eql/schema.py
eql/shell.py
eql/signatures.py
eql/table.py
eql/transpilers.py
eql/types.py
eql/utils.py
eql/walkers.py
eql/etc/__init__.py
eql/etc/eql.g
eql/etc/test_data.json
eql/etc/test_folding.toml
eql/etc/test_optimizer.toml
eql/etc/test_queries.toml
eql/etc/test_string_functions.toml
eql/tests/__init__.py
eql/tests/base.py
eql-0.9.19.dist-info/LICENSE
eql-0.9.19.dist-info/METADATA
eql-0.9.19.dist-info/WHEEL
eql-0.9.19.dist-info/entry_points.txt
eql-0.9.19.dist-info/top_level.txt
eql-0.9.19.dist-info/RECORD
