Metadata-Version: 2.1
Name: eql
Version: 0.9.19
Summary: Event Query Language
Home-page: https://eql.readthedocs.io
Author: Endgame, Inc.
Author-email: eql@endgame.com
License: AGPLv3
Classifier: Intended Audience :: Developers
Classifier: Intended Audience :: Information Technology
Classifier: Intended Audience :: Science/Research
Classifier: Intended Audience :: System Administrators
Classifier: Natural Language :: English
Classifier: Programming Language :: Python :: 2
Classifier: Programming Language :: Python :: 2.7
Classifier: Programming Language :: Python :: 3
Classifier: Programming Language :: Python :: 3.4
Classifier: Programming Language :: Python :: 3.5
Classifier: Programming Language :: Python :: 3.6
Classifier: Programming Language :: Python :: 3.7
Classifier: Topic :: Database
Classifier: Topic :: Internet :: Log Analysis
Classifier: Topic :: Scientific/Engineering :: Information Analysis
License-File: LICENSE
Requires-Dist: lark-parser (~=0.12.0)
Requires-Dist: ipaddress ; python_version < "3"
Requires-Dist: enum34 ; python_version < "3.4"
Provides-Extra: cli
Requires-Dist: pygments ; extra == 'cli'
Requires-Dist: prompt-toolkit ; extra == 'cli'
Provides-Extra: docs
Requires-Dist: sphinx ; extra == 'docs'
Requires-Dist: sphinx-rtd-theme ; extra == 'docs'
Provides-Extra: highlighters
Requires-Dist: pygments ; extra == 'highlighters'
Provides-Extra: lint
Requires-Dist: mock (~=1.3.0) ; extra == 'lint'
Requires-Dist: pytest (~=3.8.2) ; extra == 'lint'
Requires-Dist: pytest-cov (==2.4) ; extra == 'lint'
Requires-Dist: flake8 (==2.5.1) ; extra == 'lint'
Requires-Dist: pep257 (==0.7.0) ; extra == 'lint'
Requires-Dist: coverage (==4.5.3) ; extra == 'lint'
Requires-Dist: flake8-pep257 (==1.0.5) ; extra == 'lint'
Requires-Dist: toml (~=0.10) ; extra == 'lint'
Requires-Dist: contextlib2 (~=0.6.0) ; extra == 'lint'
Requires-Dist: attrs (==21.4.0) ; extra == 'lint'
Requires-Dist: PyYAML (<6.0) ; (python_version < "3.4") and extra == 'lint'
Requires-Dist: pluggy (==1.0.0-dev0) ; (python_version < "3.4") and extra == 'lint'
Requires-Dist: configparser (<5.0) ; (python_version < "3.4") and extra == 'lint'
Requires-Dist: more-itertools (~=5.0) ; (python_version < "3.4") and extra == 'lint'
Requires-Dist: importlib-metadata (<3.0) ; (python_version < "3.4") and extra == 'lint'
Requires-Dist: zipp (<1.0) ; (python_version < "3.4") and extra == 'lint'
Requires-Dist: PyYAML ; (python_version >= "3.4") and extra == 'lint'
Provides-Extra: loaders
Requires-Dist: pyyaml ; extra == 'loaders'
Requires-Dist: toml ; extra == 'loaders'
Provides-Extra: test
Requires-Dist: mock (~=1.3.0) ; extra == 'test'
Requires-Dist: pytest (~=3.8.2) ; extra == 'test'
Requires-Dist: pytest-cov (==2.4) ; extra == 'test'
Requires-Dist: flake8 (==2.5.1) ; extra == 'test'
Requires-Dist: pep257 (==0.7.0) ; extra == 'test'
Requires-Dist: coverage (==4.5.3) ; extra == 'test'
Requires-Dist: flake8-pep257 (==1.0.5) ; extra == 'test'
Requires-Dist: toml (~=0.10) ; extra == 'test'
Requires-Dist: contextlib2 (~=0.6.0) ; extra == 'test'
Requires-Dist: attrs (==21.4.0) ; extra == 'test'
Requires-Dist: PyYAML (<6.0) ; (python_version < "3.4") and extra == 'test'
Requires-Dist: pluggy (==1.0.0-dev0) ; (python_version < "3.4") and extra == 'test'
Requires-Dist: configparser (<5.0) ; (python_version < "3.4") and extra == 'test'
Requires-Dist: more-itertools (~=5.0) ; (python_version < "3.4") and extra == 'test'
Requires-Dist: importlib-metadata (<3.0) ; (python_version < "3.4") and extra == 'test'
Requires-Dist: zipp (<1.0) ; (python_version < "3.4") and extra == 'test'
Requires-Dist: PyYAML ; (python_version >= "3.4") and extra == 'test'
